{
"type": "FeatureCollection",
"name": "Request",
"crs": { "type": "name", "properties": { "name": "urn:ogc:def:crs:OGC:1.3:CRS84" } },
"features": [
{ "type": "Feature", "properties": { "Latitude": 41.9027835, "Longitude": 12.4963655, "location": "Rome", "ID": "EV81", "min start day": null, "min start month": "April", "min start year": 1133, "max start day": null, "max start month": null, "max start year": null, "min end day": null, "min end month": null, "min end year": null, "max end day": null, "max end month": null, "max end year": 1133, "type": "Request", "short description": "Rainulf II and Robert II Approach Lothar for Aid Against Roger II", "description": "Rainulf II and Robert II travel to Rome and attempt to garner Lothar's aid, but fail to do so.", "people": "Lothar, King of the Germans\nRainulf II, Count of Caiazzo and Alife\nRobert II, Prince of the Capuans", "field_21": null, "country": "Italy", "geonames url": "http:\/\/www.geonames.org\/3169070\/rome.html", "source": "The History of the Most Serene Roger, First King of Sicily in Roger II and the Creation of the Kingdom of Siclly, trans. and ed. Graham A. Loud (Manchester, Eng. and New York: Manchester University Press, 2012).", "page numbers": "91", "notes": null }, "geometry": { "type": "Point", "coordinates": [ 12.4963655, 41.9027835 ] } },
{ "type": "Feature", "properties": { "Latitude": 40.6824408, "Longitude": 14.7680961, "location": "Salerno", "ID": "EV186", "min start day": null, "min start month": null, "min start year": 1135, "max start day": null, "max start month": null, "max start year": null, "min end day": null, "min end month": null, "min end year": null, "max end day": null, "max end month": null, "max end year": 1135, "type": "Request", "short description": "Abbot Alexander of Telese Sends Request for Silver", "description": "The prior Stephen was sent to Roger II while he was in Salerno to request silver for the altar pieces taken by Rainulf II.  The silver was given, and the prior returned.", "people": "Roger II, King\nAlexander, Abbot of Telese\nStephen, prior", "field_21": null, "country": "Italy", "geonames url": "http:\/\/www.geonames.org\/11126888\/duomo-di-salerno.html", "source": "The History of the Most Serene Roger, First King of Sicily in Roger II and the Creation of the Kingdom of Siclly, trans. and ed. Graham A. Loud (Manchester, Eng. and New York: Manchester University Press, 2012).", "page numbers": "120", "notes": null }, "geometry": { "type": "Point", "coordinates": [ 14.7680961, 40.6824408 ] } }
]
}
